<?xml version="1.0" encoding="utf-8"?>
<clustering>
  <cluster type="person" id="ann_hill-01">
    <page url="http://www.ohsu.edu/pmcb/facultyresearch/hill.shtml"
    id="005" />
    <page url="http://www.ohsu.edu/microbiology/hill.html"
    id="006" />
    <page url="http://137.53.1.40/som-microbio/hill.html"
    id="020" />
    <page url="http://www.facultyof1000.com/about/biography/48376262297156"
    id="004" />
  </cluster>
  <cluster type="person" id="ann_hill-02">
    <page url="http://members.aol.com/rphs44/ahcleebio.html"
    id="001" />
    <page url="http://members.aol.com/rphs44/ahclee.html"
    id="022" />
  </cluster>
  <cluster type="person" id="ann_hill-03">
    <page url="http://www.archimuse.com/mw2000/bios/au_105011407.html"
    id="014" />
    <page url="http://www.ebookmall.com/ebook/128874-ebook.htm"
    id="045" />
    <page url="http://www.smoothreading.com/professional-technical/technology-learning/-b000066bru.htm"
    id="104" />
    <page url="http://tc.eserver.org/authors/duin,_ann_hill,_linda_a._jorn_and_lisa_mason"
    id="008" />
    <page url="http://tc.eserver.org/authors/duin,_ann_hill"
    id="011" />
    <page url="http://www.elx.com.au/item/0787950122" id="080" />
  </cluster>
  <cluster type="person" id="ann_hill-04">
    <page url="http://www.altierirealestate.com/whoweare/team/index.cfm?fuseaction=detail&amp;id=8" />
  </cluster>
  <cluster type="person" id="ann_hill-05">
    <page url="http://www.mugshots.com/criminal/killers/jessica+ann+hill.htm"
    id="021" />
  </cluster>
  <cluster type="person" id="ann_hill-07">
    <page url="http://images.halinet.on.ca/details.asp?id=4941&amp;number=79" />
  </cluster>
  <cluster type="person" id="ann_hill-08">
    <page url="http://www.nau.edu/hrm/people/f_hill.html"
    id="087" />
  </cluster>
  <cluster type="person" id="ann_hill-09">
    <page url="http://www.hillraifordbullard.com/ps03/ps03_017.html"
    id="042" />
    <page url="http://www.hillraifordbullard.com/wc02/wc02_286.html"
    id="052" />
  </cluster>
  <cluster type="person" id="ann_hill-10">
    <page url="http://www.holcombegenealogy.com/data/p15.htm"
    id="090" />
  </cluster>
  <cluster type="person" id="ann_hill-11">
    <page url="http://www.nvo.com/ecnewletter/mypage/" id="103" />
    <page url="http://www.nvo.com/ecnewletter" id="086" />
  </cluster>
  <cluster type="organization" id="ann_hill-12">
    <page url="http://www.themodernantiquarian.com/post/13508"
    id="043" />
    <page url="http://www.navicache.com/cgi-bin/db/displaycache.pl?cacheid=219"
    id="064" />
    <page url="http://www.themodernantiquarian.com/site/3586"
    id="017" />
    <page url="http://www.surreycc.gov.uk/sccwebsite/sccwspages.nsf/lookupwebpagesbytitle_rtf/72+-+st+ann's+hill?opendocument"
    id="009" />
    <page url="http://www.york.ac.uk/depts/arch/landscapes/ukpg/sites/stannshi.htm"
    id="063" />
    <page url="http://www.knightfrankglobal.com/dreamhomes/ammonite/"
    id="069" />
    <page url="http://www.davidrumsey.com/amico/amico498459-2325.html"
    id="068" />
    <page url="http://204.60.95.138/hayes1966/guy/stanneshill.htm"
    id="036" />
  </cluster>
  <cluster type="person" id="ann_hill-13">
    <page url="http://www.ecu.edu/radiationoncology/faculty/ac_vitae.html"
    id="070" />
  </cluster>
  <cluster type="person" id="ann_hill-14">
    <page url="http://w5.usc.edu:9673/asia/trustee?rec_id=5"
    id="077" />
  </cluster>
  <cluster type="person" id="ann_hill-17">
    <page url="http://dreamtalk.hypermart.net/member/files/ann_hill.html"
    id="034" />
  </cluster>
  <cluster type="person" id="ann_hill-18">
    <page url="http://www.christopherbetts.com/annh.html"
    id="018" />
  </cluster>
  <cluster type="person" id="ann_hill-19">
    <page url="http://www.apackrat.com/books/nature/search/ruth+ann+hill/"
    id="050" />
    <page url="http://books.boatdesign.net/bbwr/books.cgi?mode=books&amp;search_type=authorsearch&amp;input_string=ruth+ann+hill&amp;locale=us" />
    <page url="http://www.findbookreport.com/210607_ruth-ann-hill.html"
    id="108" />
  </cluster>
  <cluster type="person" id="ann_hill-20">
    <page url="http://c250.columbia.edu/c250_celebrates/your_columbians/ann_hill.html"
    id="007" />
  </cluster>
  <cluster type="notclassified" id="ann_hill-21">
    <page url="http://www.archinform.net/projekte/2612.htm"
    id="033" />
    <page url="http://www.buy.com/prod/ophelia_s_winter/q/loc/106/30661981.html"
    id="101" />
    <page url="http://bobqat.com/mazama/seasons/f056.html"
    id="028" />
    <page url="http://www.guilford.edu/artgallery/collect/artlist/h/hill/hill.htm"
    id="073" />
    <page url="http://www.fortunecity.co.uk/picnicpark/rainbow/134/d0000/g0000074.html"
    id="046" />
    <page url="http://freepages.genealogy.rootsweb.com/~bamkin/johnandsarahannwoolman.htm"
    id="062" />
    <page url="http://www.geocities.com/happycloudprod/annhill.html"
    id="012" />
  </cluster>
  <cluster type="person" id="ann_hill-22">
    <page url="http://www.shirleyannhill.com/" id="024" />
    <page url="http://browse.addall.com/author/10157496-1"
    id="059" />
  </cluster>
  <cluster type="person" id="ann_hill-23">
    <page url="http://www.drawntogether.com/" id="098" />
    <page url="http://www.drawntogether.com/resume.htm" id="085" />
  </cluster>
  <cluster type="person" id="ann_hill-24">
    <page url="http://familytreemaker.genealogy.com/users/h/i/l/jo-ann-hill-lutes/"
    id="013" />
  </cluster>
  <cluster type="person" id="ann_hill-26">
    <page url="http://www.beesojones.pwp.blueyonder.co.uk/ind00288.htm"
    id="002" />
  </cluster>
  <cluster type="person" id="ann_hill-28">
    <page url="http://www.bdragon.com/cgi-bin/genealogy/tree.cgi/i0795.html"
    id="010" />
  </cluster>
  <cluster type="person" id="ann_hill-29">
    <page url="http://www.distantcousin.com/homepages/sites/6/000649.html"
    id="019" />
  </cluster>
  <cluster type="person" id="ann_hill-30">
    <page url="http://www.hants.gov.uk/istcclr/cchc2315.html"
    id="023" />
  </cluster>
  <cluster type="ambiguous" id="ann_hill-31">
    <page url="http://home.att.net/~ancestralarchives/hill2.html"
    id="075" />
    <page url="http://www.wardjc.com/people/p00000pk.htm"
    id="029" />
    <page url="http://www.aemyers.net/genealogy/d0001/g0000089.html"
    id="053" />
    <page url="http://www.ronulrich.com/rfuged/fam02704.htm"
    id="058" />
    <page url="http://freepages.genealogy.rootsweb.com/~milingenealogy/d746.html"
    id="061" />
    <page url="http://www.gbso.net/actor/data/index/ind0550.html"
    id="109" />
    <page url="http://www.immigrantships.net/1800/issabella490511.html"
    id="094" />
    <page url="http://www.angelfire.com/ok2/hillresearch/hillfindings.html"
    id="074" />
    <page url="http://www.bobfears.com/results.asp?name=hill"
    id="106" />
  </cluster>
  <cluster type="person" id="ann_hill-32">
    <page url="http://www.scifan.com/writers/hh/hillaelizabeth.asp"
    id="030" />
  </cluster>
  <cluster type="person" id="ann_hill-33">
    <page url="http://www.familyorigins.com/users/k/e/e/louis-j-keester/famo1-0001/d224.htm"
    id="031" />
  </cluster>
  <cluster type="person" id="ann_hill-34">
    <page url="http://www.pollyklaas.org/missing/kids/hillt.htm"
    id="032" />
  </cluster>
  <cluster type="person" id="ann_hill-35">
    <page url="http://members.iinet.net.au/~taipan/347.htm"
    id="038" />
  </cluster>
  <cluster type="person" id="ann_hill-36">
    <page url="http://www.lib.unc.edu/mss/inv/e/elliott,lucy_ann_hill.html"
    id="039" />
  </cluster>
  <cluster type="person" id="ann_hill-37">
    <page url="http://www.newmediamarkets.com/jamesharper/docgen/d0011/g0000027.html"
    id="041" />
  </cluster>
  <cluster type="person" id="ann_hill-38">
    <page url="http://www.angelfire.com/folk/morgan/fam/fam00241.htm"
    id="049" />
  </cluster>
  <cluster type="person" id="ann_hill-40">
    <page url="http://home.quicknet.nl/qn/prive/tgeiger/genealogy/hill/1846_mary_ann_hill.htm"
    id="055" />
  </cluster>
  <cluster type="person" id="ann_hill-41">
    <page url="http://www.zaadz.com/quotes/authors/julie_ann_hill/"
    id="056" />
  </cluster>
  <cluster type="person" id="ann_hill-42">
    <page url="http://castoconnections.com/gedcom/d71.htm"
    id="060" />
  </cluster>
  <cluster type="person" id="ann_hill-44">
    <page url="http://homepages.ihug.co.nz/~wilsod/fam/fam00397.html"
    id="110" />
  </cluster>
  <cluster type="person" id="ann_hill-46">
    <page url="http://www.treetracer.com/trees/hallstanton/d0015/g0000083.html"
    id="107" />
  </cluster>
  <cluster type="person" id="ann_hill-47">
    <page url="http://www.gbnf.com/genealogy/rockwell/html/index/ind0006.htm"
    id="105" />
  </cluster>
  <cluster type="person" id="ann_hill-48">
    <page url="http://www.higherthings.org/imgs/content/shatteredchalice-text.htm"
    id="100" />
  </cluster>
  <cluster type="person" id="ann_hill-49">
    <page url="http://www.aemyers.net/genealogy/d0005/g0000058.html"
    id="097" />
  </cluster>
  <cluster type="person" id="ann_hill-50">
    <page url="http://www.coylecassidy.com/homework/mhill.html"
    id="096" />
  </cluster>
  <cluster type="person" id="ann_hill-52">
    <page url="http://www.open.org/rumcd/d0000/g0000059.htm"
    id="092" />
    <page url="http://www.open.org/rumcd/index/ind0038.htm"
    id="072" />
  </cluster>
  <cluster type="person" id="ann_hill-53">
    <page url="http://www.farrant.info/family/ghtout/gp180.html"
    id="091" />
  </cluster>
  <cluster type="person" id="ann_hill-54">
    <page url="http://www.tech2u.com.au/~normtew/sbn/pafg33.htm"
    id="089" />
  </cluster>
  <cluster type="person" id="ann_hill-55">
    <page url="http://www.toowongwest.org.au/history/ann-hill-03.htm"
    id="088" />
    <page url="http://www.toowongwest.org.au/history/ann_hill_01.htm"
    id="027" />
  </cluster>
  <cluster type="person" id="ann_hill-56">
    <page url="http://www.donwingfield.net/tmgdata/p184.htm"
    id="084" />
  </cluster>
  <cluster type="person" id="ann_hill-57">
    <page url="http://www.hal-pc.org/~wibr/d88.htm" id="082" />
  </cluster>
  <cluster type="person" id="ann_hill-58">
    <page url="http://genforum.com/higdon/messages/852.html"
    id="079" />
  </cluster>
  <cluster type="person" id="ann_hill-59">
    <page url="http://www.ballaratgenealogy.org.au/digby/family/annett.htm"
    id="076" />
  </cluster>
  <cluster type="person" id="ann_hill-61">
    <page url="http://www.smokykin.com/ged/f006/f45/a0064588.htm"
    id="071" />
  </cluster>
  <cluster type="person" id="ann_hill-62">
    <page url="http://knibbs.family.users.btopenworld.com/fam081.html"
    id="067" />
  </cluster>
  <cluster type="person" id="ann_hill-63">
    <page url="http://www.smokykin.com/ged/f003/f42/a0034279.htm"
    id="066" />
  </cluster>
  <cluster type="person" id="ann_hill-64">
    <page url="http://www.biffle.org/fgs-johnsonlacy.html"
    id="065" />
  </cluster>
  <cluster type="organization" id="ann_hill-65">
    <page url="http://www.hants.gov.uk/press/2002/buryroad.html"
    id="040" />
  </cluster>
  <cluster type="person" id="ann_hill-66">
    <page url="http://users.quista.net/dgnhas/ann-hill/ann%20hill%20bequest.htm"
    id="047" />
  </cluster>
  <cluster type="organization" id="ann_hill-67">
    <page url="http://www.envf.port.ac.uk/hantsgaz/hantsgaz/s0000207.htm"
    id="093" />
  </cluster>
  <cluster type="person" id="ann_hill-69">
    <page url="http://www.smartvoter.org/2002/11/05/ca/state/vote/hill_ja/"
    id="015" />
    <page url="http://www.smartvoter.org/2002/03/05/ca/state/vote/hill_ja/"
    id="016" />
  </cluster>
  <cluster type="person" id="ann_hill-70">
    <page url="http://www.drpatriciahill.com/drhill.htm"
    id="102" />
  </cluster>
  <cluster type="person" id="ann_hill-71">
    <page url="http://www.ac.aup.fr/ecspl/alumni/ann.htm"
    id="003" />
  </cluster>
</clustering>
